{

"Trade_12064":{
"id":"12064",
"order_id":"null",
"exchange":"ccedk",
"pair":"nbtbtc",
"type":"SELL",
"price":0.00267922,
"amount":2.75,
"fee":0.00001473,
"timestamp":1417399387000
},

"Trade_12052":{
"id":"12052",
"order_id":"null",
"exchange":"ccedk",
"pair":"nbtbtc",
"type":"SELL",
"price":0.00266334,
"amount":345.69375296,
"fee":0.00184139,
"timestamp":1417398217000
},

"Trade_11890":{
"id":"11890",
"order_id":"null",
"exchange":"ccedk",
"pair":"nbtbtc",
"type":"SELL",
"price":0.00266866,
"amount":263.91522337,
"fee":0.00140859,
"timestamp":1417377950000
},

"Trade_11836":{
"id":"11836",
"order_id":"null",
"exchange":"ccedk",
"pair":"nbtbtc",
"type":"SELL",
"price":0.00267378,
"amount":1838.69652701,
"fee":0.00983253,
"timestamp":1417366612000
},

"Trade_11424":{
"id":"11424",
"order_id":"null",
"exchange":"ccedk",
"pair":"nbtbtc",
"type":"SELL",
"price":0.00267757,
"amount":37.0,
"fee":0.00019814,
"timestamp":1417322807000
},

"Trade_11091":{
"id":"11091",
"order_id":"null",
"exchange":"ccedk",
"pair":"nbtbtc",
"type":"BUY",
"price":0.00262881,
"amount":1133.0,
"fee":2.266,
"timestamp":1417262010000
},

"Trade_11090":{
"id":"11090",
"order_id":"null",
"exchange":"ccedk",
"pair":"nbtbtc",
"type":"SELL",
"price":0.00264366,
"amount":1134.79040421,
"fee":0.00599999,
"timestamp":1417261332000
},

"Trade_11082":{
"id":"11082",
"order_id":"null",
"exchange":"ccedk",
"pair":"nbtbtc",
"type":"SELL",
"price":0.00264059,
"amount":149.0,
"fee":0.00078689,
"timestamp":1417212089000
},

"Trade_10962":{
"id":"10962",
"order_id":"null",
"exchange":"ccedk",
"pair":"nbtbtc",
"type":"SELL",
"price":0.0026415,
"amount":462.37954571,
"fee":0.00244275,
"timestamp":1417207128000
},

"Trade_10915":{
"id":"10915",
"order_id":"null",
"exchange":"ccedk",
"pair":"nbtbtc",
"type":"BUY",
"price":0.00264693,
"amount":500.0,
"fee":1,
"timestamp":1417205199000
},

"Trade_10788":{
"id":"10788",
"order_id":"null",
"exchange":"ccedk",
"pair":"nbtbtc",
"type":"SELL",
"price":0.00270884,
"amount":9064.24130993,
"fee":0.04910715,
"timestamp":1417188455000
},

"Trade_10785":{
"id":"10785",
"order_id":"null",
"exchange":"ccedk",
"pair":"nbtbtc",
"type":"BUY",
"price":0.0027049,
"amount":50.0,
"fee":0.1,
"timestamp":1417188226000
},

"Trade_10783":{
"id":"10783",
"order_id":"null",
"exchange":"ccedk",
"pair":"nbtbtc",
"type":"SELL",
"price":0.00271942,
"amount":5000.0,
"fee":10,
"timestamp":1417187902000
},

"Trade_10781":{
"id":"10781",
"order_id":"null",
"exchange":"ccedk",
"pair":"nbtbtc",
"type":"BUY",
"price":0.00271942,
"amount":2000.0,
"fee":4,
"timestamp":1417187849000
},

"Trade_10779":{
"id":"10779",
"order_id":"null",
"exchange":"ccedk",
"pair":"nbtbtc",
"type":"BUY",
"price":0.00271942,
"amount":1000.0,
"fee":2,
"timestamp":1417187830000
},

"Trade_10777":{
"id":"10777",
"order_id":"null",
"exchange":"ccedk",
"pair":"nbtbtc",
"type":"BUY",
"price":0.00271218,
"amount":1000.0,
"fee":2,
"timestamp":1417187776000
},

"Trade_10774":{
"id":"10774",
"order_id":"null",
"exchange":"ccedk",
"pair":"nbtbtc",
"type":"SELL",
"price":0.00273002,
"amount":2004.61636911,
"fee":0.01094528,
"timestamp":1417186718000
},

"Trade_10771":{
"id":"10771",
"order_id":"null",
"exchange":"ccedk",
"pair":"nbtbtc",
"type":"BUY",
"price":0.00274734,
"amount":1000.0,
"fee":2,
"timestamp":1417184406000
},

"Trade_10769":{
"id":"10769",
"order_id":"null",
"exchange":"ccedk",
"pair":"nbtbtc",
"type":"BUY",
"price":0.00273627,
"amount":1000.0,
"fee":2,
"timestamp":1417181760000
},

"Trade_10538":{
"id":"10538",
"order_id":"null",
"exchange":"ccedk",
"pair":"nbtbtc",
"type":"SELL",
"price":0.0027073,
"amount":63.54716876,
"fee":0.00034408,
"timestamp":1417113933000
},

"Trade_10517":{
"id":"10517",
"order_id":"null",
"exchange":"ccedk",
"pair":"nbtbtc",
"type":"BUY",
"price":0.00268612,
"amount":186.14209343,
"fee":0.37228418,
"timestamp":1417099557000
},

"Trade_10515":{
"id":"10515",
"order_id":"null",
"exchange":"ccedk",
"pair":"nbtbtc",
"type":"BUY",
"price":0.00268612,
"amount":372.28418686,
"fee":0.74456836,
"timestamp":1417099497000
},

"Trade_10510":{
"id":"10510",
"order_id":"null",
"exchange":"ccedk",
"pair":"nbtbtc",
"type":"SELL",
"price":0.00270197,
"amount":304.69624385,
"fee":0.00164656,
"timestamp":1417097421000
},

"Trade_10504":{
"id":"10504",
"order_id":"null",
"exchange":"ccedk",
"pair":"nbtbtc",
"type":"SELL",
"price":0.00268957,
"amount":243.75,
"fee":0.00131116,
"timestamp":1417084159000
},

"Trade_10487":{
"id":"10487",
"order_id":"null",
"exchange":"ccedk",
"pair":"nbtbtc",
"type":"BUY",
"price":0.00268699,
"amount":111.64909434,
"fee":0.22329818,
"timestamp":1417076015000
},

"Trade_10459":{
"id":"10459",
"order_id":"null",
"exchange":"ccedk",
"pair":"nbtbtc",
"type":"BUY",
"price":0.00267776,
"amount":1874.0,
"fee":3.748,
"timestamp":1417060826000
},

"Trade_10458":{
"id":"10458",
"order_id":"null",
"exchange":"ccedk",
"pair":"nbtbtc",
"type":"SELL",
"price":0.00271038,
"amount":155.80737387,
"fee":0.00084459,
"timestamp":1417052837000
},

"Trade_10456":{
"id":"10456",
"order_id":"null",
"exchange":"ccedk",
"pair":"nbtbtc",
"type":"SELL",
"price":0.00270023,
"amount":40304.0,
"fee":0.21766013,
"timestamp":1417052162000
},

"Trade_10401":{
"id":"10401",
"order_id":"null",
"exchange":"ccedk",
"pair":"nbtbtc",
"type":"BUY",
"price":0.00268474,
"amount":1795.05519343,
"fee":3.59011038,
"timestamp":1417046896000
},

"Trade_10399":{
"id":"10399",
"order_id":"null",
"exchange":"ccedk",
"pair":"nbtbtc",
"type":"BUY",
"price":0.00268474,
"amount":1795.05519715,
"fee":3.59011038,
"timestamp":1417046896000
},

"Trade_10354":{
"id":"10354",
"order_id":"null",
"exchange":"ccedk",
"pair":"nbtbtc",
"type":"SELL",
"price":0.00266206,
"amount":1878.24466766,
"fee":0.00999999,
"timestamp":1417018893000
},

"Trade_10255":{
"id":"10255",
"order_id":"null",
"exchange":"ccedk",
"pair":"nbtbtc",
"type":"BUY",
"price":0.00265935,
"amount":1114.0,
"fee":2.228,
"timestamp":1417016182000
},

"Trade_9952":{
"id":"9952",
"order_id":"null",
"exchange":"ccedk",
"pair":"nbtbtc",
"type":"SELL",
"price":0.00268079,
"amount":373.02436968,
"fee":0.00199999,
"timestamp":1417008027000
},

"Trade_9942":{
"id":"9942",
"order_id":"null",
"exchange":"ccedk",
"pair":"nbtbtc",
"type":"SELL",
"price":0.00268388,
"amount":742.49522947,
"fee":0.00398553,
"timestamp":1417007329000
},

"Trade_9833":{
"id":"9833",
"order_id":"null",
"exchange":"ccedk",
"pair":"nbtbtc",
"type":"BUY",
"price":0.00268974,
"amount":362.2368,
"fee":0.7244736,
"timestamp":1417002737000
},

"Trade_9784":{
"id":"9784",
"order_id":"null",
"exchange":"ccedk",
"pair":"nbtbtc",
"type":"SELL",
"price":0.00269601,
"amount":1588.522958,
"fee":0.00856534,
"timestamp":1416999927000
},

"Trade_9732":{
"id":"9732",
"order_id":"null",
"exchange":"ccedk",
"pair":"nbtbtc",
"type":"SELL",
"price":0.00265423,
"amount":500.0,
"fee":0.00265423,
"timestamp":1416983887000
},

"Trade_9729":{
"id":"9729",
"order_id":"null",
"exchange":"ccedk",
"pair":"nbtbtc",
"type":"BUY",
"price":0.00265751,
"amount":807.38290731,
"fee":1.6147658,
"timestamp":1416972461000
},

"Trade_9727":{
"id":"9727",
"order_id":"null",
"exchange":"ccedk",
"pair":"nbtbtc",
"type":"BUY",
"price":0.00265751,
"amount":807.38290355,
"fee":1.6147658,
"timestamp":1416972461000
},

"Trade_9726":{
"id":"9726",
"order_id":"null",
"exchange":"ccedk",
"pair":"nbtbtc",
"type":"SELL",
"price":0.00268741,
"amount":600.0,
"fee":0.00322489,
"timestamp":1416971610000
},

"Trade_9724":{
"id":"9724",
"order_id":"null",
"exchange":"ccedk",
"pair":"nbtbtc",
"type":"SELL",
"price":0.00268741,
"amount":500.0,
"fee":0.00268741,
"timestamp":1416971120000
},

"Trade_9722":{
"id":"9722",
"order_id":"null",
"exchange":"ccedk",
"pair":"nbtbtc",
"type":"SELL",
"price":0.00268741,
"amount":500.0,
"fee":0.00268741,
"timestamp":1416971085000
},

"Trade_9719":{
"id":"9719",
"order_id":"null",
"exchange":"ccedk",
"pair":"nbtbtc",
"type":"BUY",
"price":0.00266909,
"amount":8365.17073235,
"fee":16.73034146,
"timestamp":1416968659000
},

"Trade_9717":{
"id":"9717",
"order_id":"null",
"exchange":"ccedk",
"pair":"nbtbtc",
"type":"BUY",
"price":0.00266909,
"amount":8365.17073235,
"fee":16.73034146,
"timestamp":1416968659000
},

"Trade_9715":{
"id":"9715",
"order_id":"null",
"exchange":"ccedk",
"pair":"nbtbtc",
"type":"BUY",
"price":0.00267066,
"amount":4114.0,
"fee":8.228,
"timestamp":1416967251000
},

"Trade_9713":{
"id":"9713",
"order_id":"null",
"exchange":"ccedk",
"pair":"nbtbtc",
"type":"BUY",
"price":0.00266254,
"amount":2651.0,
"fee":5.302,
"timestamp":1416966711000
},

"Trade_9711":{
"id":"9711",
"order_id":"null",
"exchange":"ccedk",
"pair":"nbtbtc",
"type":"BUY",
"price":0.00267209,
"amount":4072.0,
"fee":8.144,
"timestamp":1416965760000
},

"Trade_9699":{
"id":"9699",
"order_id":"null",
"exchange":"ccedk",
"pair":"nbtbtc",
"type":"BUY",
"price":0.00264967,
"amount":4065.0,
"fee":8.13,
"timestamp":1416952693000
},

"Trade_9679":{
"id":"9679",
"order_id":"null",
"exchange":"ccedk",
"pair":"nbtbtc",
"type":"BUY",
"price":0.00260072,
"amount":1957.0,
"fee":3.914,
"timestamp":1416922978000
},

"Trade_9677":{
"id":"9677",
"order_id":"null",
"exchange":"ccedk",
"pair":"nbtbtc",
"type":"BUY",
"price":0.0025717,
"amount":4200.37676751,
"fee":8.40075352,
"timestamp":1416918315000
},

"Trade_9676":{
"id":"9676",
"order_id":"null",
"exchange":"ccedk",
"pair":"nbtbtc",
"type":"SELL",
"price":0.00255573,
"amount":4208.79435621,
"fee":0.02151308,
"timestamp":1416917264000
},

"Trade_9674":{
"id":"9674",
"order_id":"null",
"exchange":"ccedk",
"pair":"nbtbtc",
"type":"SELL",
"price":0.00254897,
"amount":33224.4004441,
"fee":0.16937599,
"timestamp":1416917086000
},

"Trade_9672":{
"id":"9672",
"order_id":"null",
"exchange":"ccedk",
"pair":"nbtbtc",
"type":"SELL",
"price":0.00254897,
"amount":1961.57663684,
"fee":0.00999999,
"timestamp":1416917042000
},

"Trade_9669":{
"id":"9669",
"order_id":"null",
"exchange":"ccedk",
"pair":"nbtbtc",
"type":"BUY",
"price":0.00254644,
"amount":16662.07264652,
"fee":33.32414528,
"timestamp":1416916249000
},

"Trade_9667":{
"id":"9667",
"order_id":"null",
"exchange":"ccedk",
"pair":"nbtbtc",
"type":"BUY",
"price":0.00254644,
"amount":16662.07264652,
"fee":33.32414528,
"timestamp":1416916249000
},

"Trade_9665":{
"id":"9665",
"order_id":"null",
"exchange":"ccedk",
"pair":"nbtbtc",
"type":"BUY",
"price":0.00255223,
"amount":782.0,
"fee":1.564,
"timestamp":1416915987000
},

"Trade_9664":{
"id":"9664",
"order_id":"null",
"exchange":"ccedk",
"pair":"nbtbtc",
"type":"SELL",
"price":0.00255254,
"amount":783.5332649,
"fee":0.00399999,
"timestamp":1416912937000
},

"Trade_9661":{
"id":"9661",
"order_id":"null",
"exchange":"ccedk",
"pair":"nbtbtc",
"type":"BUY",
"price":0.0025647,
"amount":4202.47912677,
"fee":8.40495824,
"timestamp":1416912027000
},

"Trade_9658":{
"id":"9658",
"order_id":"null",
"exchange":"ccedk",
"pair":"nbtbtc",
"type":"SELL",
"price":0.00254897,
"amount":4210.90092861,
"fee":0.02146692,
"timestamp":1416909253000
},

"Trade_9655":{
"id":"9655",
"order_id":"null",
"exchange":"ccedk",
"pair":"nbtbtc",
"type":"BUY",
"price":0.00254196,
"amount":4230.97530444,
"fee":8.4619506,
"timestamp":1416908051000
},

"Trade_9654":{
"id":"9654",
"order_id":"null",
"exchange":"ccedk",
"pair":"nbtbtc",
"type":"SELL",
"price":0.00253652,
"amount":4239.45421286,
"fee":0.02150692,
"timestamp":1416906935000
},

"Trade_9649":{
"id":"9649",
"order_id":"null",
"exchange":"ccedk",
"pair":"nbtbtc",
"type":"BUY",
"price":0.00259356,
"amount":52.7173685,
"fee":0.10543472,
"timestamp":1416898908000
},

"Trade_9643":{
"id":"9643",
"order_id":"null",
"exchange":"ccedk",
"pair":"nbtbtc",
"type":"BUY",
"price":0.00262266,
"amount":4108.42828944,
"fee":8.21685656,
"timestamp":1416891289000
},

"Trade_9641":{
"id":"9641",
"order_id":"null",
"exchange":"ccedk",
"pair":"nbtbtc",
"type":"BUY",
"price":0.00263979,
"amount":760.0,
"fee":1.52,
"timestamp":1416888791000
},

"Trade_9640":{
"id":"9640",
"order_id":"null",
"exchange":"ccedk",
"pair":"nbtbtc",
"type":"SELL",
"price":0.00262599,
"amount":761.6175233,
"fee":0.00399999,
"timestamp":1416888551000
},

"Trade_9636":{
"id":"9636",
"order_id":"null",
"exchange":"ccedk",
"pair":"nbtbtc",
"type":"SELL",
"price":0.00259794,
"amount":4116.66161266,
"fee":0.02138967,
"timestamp":1416881995000
},

"Trade_9627":{
"id":"9627",
"order_id":"null",
"exchange":"ccedk",
"pair":"nbtbtc",
"type":"BUY",
"price":0.00265362,
"amount":4038.3598347,
"fee":8.07671966,
"timestamp":1416868509000
},

"Trade_9626":{
"id":"9626",
"order_id":"null",
"exchange":"ccedk",
"pair":"nbtbtc",
"type":"SELL",
"price":0.00258888,
"amount":4046.45274018,
"fee":0.02095156,
"timestamp":1416865146000
},

"Trade_9623":{
"id":"9623",
"order_id":"null",
"exchange":"ccedk",
"pair":"nbtbtc",
"type":"BUY",
"price":0.00261222,
"amount":4018.33464404,
"fee":8.03666928,
"timestamp":1416856022000
},

"Trade_9616":{
"id":"9616",
"order_id":"null",
"exchange":"ccedk",
"pair":"nbtbtc",
"type":"SELL",
"price":0.00263601,
"amount":4026.38741886,
"fee":0.02122719,
"timestamp":1416848027000
},

"Trade_9610":{
"id":"9610",
"order_id":"null",
"exchange":"ccedk",
"pair":"nbtbtc",
"type":"SELL",
"price":0.00263075,
"amount":2503.84717285,
"fee":0.01317399,
"timestamp":1416847862000
},

"Trade_9607":{
"id":"9607",
"order_id":"null",
"exchange":"ccedk",
"pair":"nbtbtc",
"type":"BUY",
"price":0.00265334,
"amount":4008.10572106,
"fee":8.01621144,
"timestamp":1416845158000
},

"Trade_9606":{
"id":"9606",
"order_id":"null",
"exchange":"ccedk",
"pair":"nbtbtc",
"type":"SELL",
"price":0.0026331,
"amount":4016.13799704,
"fee":0.02114978,
"timestamp":1416840992000
},

"Trade_9595":{
"id":"9595",
"order_id":"null",
"exchange":"ccedk",
"pair":"nbtbtc",
"type":"BUY",
"price":0.00268706,
"amount":749.8,
"fee":1.4996,
"timestamp":1416829855000
},

"Trade_9594":{
"id":"9594",
"order_id":"null",
"exchange":"ccedk",
"pair":"nbtbtc",
"type":"SELL",
"price":0.00266525,
"amount":750.39864928,
"fee":0.00399999,
"timestamp":1416828296000
},

"Trade_9587":{
"id":"9587",
"order_id":"null",
"exchange":"ccedk",
"pair":"nbtbtc",
"type":"BUY",
"price":0.00266055,
"amount":129.0,
"fee":0.258,
"timestamp":1416822028000
},

"Trade_9583":{
"id":"9583",
"order_id":"null",
"exchange":"ccedk",
"pair":"nbtbtc",
"type":"BUY",
"price":0.00266838,
"amount":3970.9805719,
"fee":7.94196114,
"timestamp":1416819270000
},

"Trade_9581":{
"id":"9581",
"order_id":"null",
"exchange":"ccedk",
"pair":"nbtbtc",
"type":"BUY",
"price":0.00270036,
"amount":12460.44706621,
"fee":24.92089412,
"timestamp":1416811643000
}
}
